rs_versions-0.2.0.dist-info/METADATA
rs_versions-0.2.0.dist-info/WHEEL
rs_versions/__init__.py
rs_versions/rs_versions.cpython-310-x86_64-linux-gnu.so
rs_versions-0.2.0.dist-info/RECORD
