Metadata-Version: 2.1
Name: rs_versions
Version: 0.2.0
